{
  "hanzi": "信",
  "pinyin": "xìn",
  "meaning_ru": "письмо; верить, доверять; вера",
  "meaning_en": "letter (mail); to trust, to believe; faith",
  "radicals": [
    {
      "hz": "亻",
      "name": "rén — человек",
      "note": "Левая часть. Справа 言 — «речь, слово». Человек + его слово: 信 — это и «держать слово» (верить), и «послание» (письмо)"
    },
    {
      "hz": "言",
      "name": "yán — речь, слово",
      "note": "Правая часть. Сверху чёрточки как звуки, выходящие изо рта (口 внизу). Всё, что связано с речью, носит этот ключ"
    }
  ],
  "deep_dive": "<p>信 — редкий иероглиф, где видно саму идею. Слева <strong>человек</strong> (亻), справа <strong>слово</strong> (言): человек, верный своему слову. Отсюда сразу два смысла — <strong>«верить, доверие»</strong> и <strong>«письмо»</strong> (то, в чём ты передаёшь своё слово на расстояние).</p><p>В жизни 信 чаще всего — «письмо»: 写信 (писать письмо), 一封信 (одно письмо, счётное слово 封). Но в словах живёт и «вера»: <strong>相信</strong> (xiāngxìn) — верить, <strong>信任</strong> (xìnrèn) — доверять, <strong>信心</strong> (xìnxīn) — уверенность.</p>",
  "situations": [
    {
      "title": "☁ Почта",
      "setup": "Говоришь, что получил весточку.",
      "line": "我收到一封信。 — «Я получил письмо.»"
    },
    {
      "title": "✦ Доверие",
      "setup": "Заверяешь, что доверяешь.",
      "line": "我相信你说的话。 — «Я верю твоим словам.»"
    }
  ],
  "examples": [
    {
      "cn": "我给妈妈写了一封{hl}信{/hl}。",
      "py": "wǒ gěi māma xiě le yì fēng xìn.",
      "ru": "Я написал маме письмо.",
      "note": "封 (fēng) — счётное слово для писем · 写 (xiě) — писать"
    },
    {
      "cn": "你{hl}信{/hl}我吗？",
      "py": "nǐ xìn wǒ ma?",
      "ru": "Ты мне веришь?",
      "note": "коротко — 信 здесь «верить»"
    },
    {
      "cn": "他对自己很有{hl}信{/hl}心。",
      "py": "tā duì zìjǐ hěn yǒu xìnxīn.",
      "ru": "Он очень уверен в себе.",
      "note": "信心 (xìnxīn) — уверенность · 自己 (zìjǐ) — сам"
    }
  ],
  "footer_note": "信 — письмо и вера в одном знаке (человек + слово); 一封信 одно письмо · HSK 3 (hsk2.0-L3)"
}
