{
 "hanzi": "厅",
 "pinyin": "tīng",
 "meaning_ru": "зал; гостиная; (в составе слов) ведомство, управление",
 "meaning_en": "hall; living room; (in compounds) a provincial-level government department",
 "radicals": [
  {
   "hz": "厂",
   "name": "chǎng — навес",
   "note": "Внешняя часть 厅 — крыша-навес, под которой много места. Внутри 丁 даёт звук «tīng». Большое крытое пространство — это и есть «зал»"
  }
 ],
 "deep_dive": "<p>厅 — это <strong>большое помещение для людей</strong>, а не маленькая комната. Дома это 客厅 (kètīng) — гостиная, где принимают гостей; 餐厅 (cāntīng) — столовая или ресторан; 大厅 (dàtīng) — главный зал, лобби.</p><p>Неожиданный второй смысл: 厅 — это ещё и <strong>уровень власти</strong>. 教育厅 — областное управление образования. Тот же иероглиф «зал» вырос в название чиновничьего ведомства — как русская «палата» когда-то.</p>",
 "situations": [
  {
   "title": "✦ Дома",
   "setup": "Показываешь гостю квартиру.",
   "line": "这是客厅。 — «Это гостиная.»"
  }
 ],
 "examples": [
  {
   "cn": "我们在客{hl}厅{/hl}看电视。",
   "py": "Wǒmen zài kètīng kàn diànshì.",
   "ru": "Мы смотрим телевизор в гостиной.",
   "note": "客厅 (kètīng) — гостиная"
  },
  {
   "cn": "餐{hl}厅{/hl}在二楼。",
   "py": "Cāntīng zài èr lóu.",
   "ru": "Ресторан на втором этаже.",
   "note": "餐厅 (cāntīng) — ресторан · 楼 (lóu) — этаж"
  },
  {
   "cn": "大{hl}厅{/hl}里有很多人。",
   "py": "Dàtīng lǐ yǒu hěn duō rén.",
   "ru": "В холле много людей.",
   "note": "大厅 (dàtīng) — большой зал, холл"
  }
 ],
 "footer_note": "厅 — зал: 客厅 (гостиная), 餐厅 (ресторан), 大厅 (холл) · также областное ведомство · HSK 3.0 L5"
}
