{
  "hanzi": "喊",
  "pinyin": "hǎn",
  "meaning_ru": "кричать, орать; звать (громко)",
  "meaning_en": "to shout, yell; to call out to someone",
  "radicals": [
    {
      "hz": "口",
      "name": "kǒu — рот",
      "note": "Левая часть 喊. Всё, что кричат, говорят, поют — рядом с 口. Рот — источник звука"
    }
  ],
  "deep_dive": "<p><strong>喊</strong> — это громкий звук, физическое усилие голоса. Зовёшь кого-то через двор, кричишь от боли, подбадриваешь команду на трибуне — всё это 喊.</p><p>Разница с 叫 (jiào): 叫 шире — это и «называться», и «звать», и «кричать». 喊 — только про <strong>громкий голос</strong>, ни про что другое. Когда речь о крике как физическом звуке — 喊 точнее.</p><p>Есть красивое выражение <strong>喊冤</strong> (hǎn yuān) — буквально «кричать о несправедливости». Так говорят, когда человек громко заявляет, что его обидели незаслуженно. В историческом Китае подданные могли буквально кричать перед судом чиновника — это был легальный способ привлечь внимание к своей беде.</p>",
  "situations": [
    {
      "title": "✦ На улице",
      "setup": "Зовёшь друга, который ушёл вперёд.",
      "line": "你等等！我一直在喊你！ — «Подожди! Я всё время тебя звал!»"
    },
    {
      "title": "☁ На стадионе",
      "setup": "Болельщики поддерживают свою команду.",
      "line": "大家一起喊！加油！ — «Все вместе кричите! Давай!»"
    }
  ],
  "examples": [
    {
      "cn": "他大声{hl}喊{/hl}了我的名字。",
      "py": "Tā dàshēng hǎn le wǒ de míngzi.",
      "ru": "Он громко позвал меня по имени.",
      "note": "大声 (dàshēng) — громко"
    },
    {
      "cn": "不要在图书馆{hl}喊{/hl}叫。",
      "py": "Bù yào zài túshūguǎn hǎnjiào.",
      "ru": "Не надо кричать в библиотеке.",
      "note": "图书馆 (túshūguǎn) — библиотека"
    },
    {
      "cn": "她{hl}喊{/hl}了好几声，没人回答。",
      "py": "Tā hǎn le hǎo jǐ shēng, méi rén huídá.",
      "ru": "Она крикнула несколько раз — никто не ответил.",
      "note": "声 (shēng) — раз (счётное слово для звуков) · 回答 (huídá) — отвечать"
    }
  ],
  "footer_note": "喊 — только про громкий голос; 叫 шире; 喊冤 — кричать о несправедливости · HSK 5 (hsk2.0-L5)"
}