{
  "hanzi": "尽",
  "pinyin": "jǐn",
  "meaning_ru": "как можно больше; в меру возможного; давать приоритет (чтению jǐn); исчерпывать; до конца (чтение jìn)",
  "meaning_en": "to the greatest extent; as much as possible (jǐn); to exhaust; entirely; all (jìn)",
  "radicals": [
    {
      "hz": "尽",
      "name": "— два значения, два чтения",
      "note": "Иероглиф 尽 — упрощение традиционного 盡 (кисть + посуда + вода). Образ: вычерпать сосуд дочиста — отсюда «до конца, исчерпать»"
    }
  ],
  "deep_dive": "<p><strong>尽</strong> — один из тех иероглифов с двумя чтениями, которые меняют смысл. При чтении <strong>jìn</strong> — «исчерпать, всё до конца»: <strong>用尽</strong> — истратить всё, <strong>尽力</strong> (jìn lì) — приложить все силы. При чтении <strong>jǐn</strong> — «в максимальной мере, отдавая приоритет»: <strong>尽快</strong> (jǐn kuài) — как можно скорее, <strong>尽早</strong> — как можно раньше.</p><p>На практике самые частые слова: <strong>尽管</strong> (jǐnguǎn) — «хотя, несмотря на то что» и «не стесняйся/смело (делай)», <strong>尽快</strong> — «как можно скорее». Оба — с чтением jǐn. Запомнить: jǐn — «сделай максимально», jìn — «до конца».</p>",
  "situations": [
    {
      "title": "✦ Просьба",
      "setup": "Просишь сделать что-то как можно скорее.",
      "line": "请尽快回复我。 — «Пожалуйста, ответь как можно скорее.»"
    },
    {
      "title": "☁ Усилие",
      "setup": "Говоришь, что постараешься изо всех сил.",
      "line": "我会尽力的。 — «Я постараюсь изо всех сил.»"
    }
  ],
  "examples": [
    {
      "cn": "请{hl}尽{/hl}快回复。",
      "py": "Qǐng jǐn kuài huífù.",
      "ru": "Пожалуйста, ответьте как можно скорее.",
      "note": "尽快 — как можно скорее"
    },
    {
      "cn": "我会{hl}尽{/hl}力帮你。",
      "py": "Wǒ huì jìn lì bāng nǐ.",
      "ru": "Я постараюсь изо всех сил помочь тебе.",
      "note": "尽力 (jìn lì) — приложить все усилия"
    },
    {
      "cn": "{hl}尽{/hl}管很难，他还是做完了。",
      "py": "Jǐnguǎn hěn nán, tā háishi zuòwán le.",
      "ru": "Хотя это было очень сложно, он всё равно закончил.",
      "note": "尽管 — хотя, несмотря на то что · 还是 — всё равно"
    }
  ],
  "footer_note": "尽 — два чтения: jǐn (尽快, 尽管) и jìn (尽力, 用尽) · freq rank ~1403"
}