{
  "hanzi": "帅",
  "pinyin": "shuài",
  "meaning_ru": "красивый, привлекательный (о мужчине); крутой (разг.)",
  "meaning_en": "handsome, dashing; cool, awesome (colloquial)",
  "deep_dive": "<p>帅 — это «красивый» для мужчин. Не просто симпатичный, а <strong>стильный, с харизмой, с осанкой</strong>. По-русски ближе всего «красавчик» или «крутой». Для девушек говорят 漂亮 (piàoliang) или 美 (měi), для парней — 帅 (shuài) или 好看 (hǎokàn).</p><p>В молодёжном языке 帅 давно вышло за рамки внешности: можно сказать 帅 о стильном поступке, крутом движении или элегантном решении задачи. «Это было 帅» — «это было круто».</p><p>Исторически 帅 означало «главнокомандующий» — в китайских шахматах (象棋) красная фигура «генерал» называется именно 帅. И правда: настоящий командующий должен быть внушительным и собранным. Отсюда — «красивый, элегантный».</p>",
  "situations": [
    {
      "title": "✦ Комплимент",
      "setup": "Видишь друга в новом пиджаке.",
      "line": "你今天好帅！ — «Ты сегодня такой красавчик!»"
    },
    {
      "title": "☁ Восхищение",
      "setup": "Кто-то сделал что-то ловкое или стильное.",
      "line": "太帅了！ — «Вот это круто!»"
    }
  ],
  "examples": [
    {
      "cn": "他长得很{hl}帅{/hl}。",
      "py": "Tā zhǎng de hěn shuài.",
      "ru": "Он очень красивый (внешне).",
      "note": "长得 (zhǎng de) — выглядеть, быть (о внешности)"
    },
    {
      "cn": "你穿这件衣服很{hl}帅{/hl}！",
      "py": "Nǐ chuān zhè jiàn yīfu hěn shuài!",
      "ru": "В этой одежде ты очень круто выглядишь!",
      "note": "穿 (chuān) — носить одежду"
    },
    {
      "cn": "太{hl}帅{/hl}了，我喜欢！",
      "py": "Tài shuài le, wǒ xǐhuān!",
      "ru": "Слишком круто, мне нравится!"
    }
  ],
  "footer_note": "HSK 4 (hsk2.0-L4) · для женщин: 漂亮/美 · в шахматах 象棋: красная фигура «генерал» тоже 帅"
}