{
 "hanzi": "提",
 "pinyin": "tí",
 "meaning_ru": "поднимать, нести (в руке за ручку); упоминать, поднимать (вопрос)",
 "meaning_en": "to lift; to carry (by a handle); to raise (an issue); to mention",
 "radicals": [
  {
   "hz": "扌",
   "name": "shǒu — рука",
   "note": "Левая часть 提 — «рука» (扌, сжатый 手). Почти всё, что делаешь рукой, носит этот ключ: 拿 нести, 打 бить. 提 — поднимать рукой за ручку"
  },
  {
   "hz": "是",
   "name": "shì — даёт звук",
   "note": "Правая часть 是 здесь работает как фонетик, подсказывая чтение, а не смысл"
  }
 ],
 "deep_dive": "<p>У 提 два слоя смысла, и оба идут от одного жеста — <strong>«поднять рукой»</strong>. Буквально: 提 — нести сумку или ведро за ручку, держа на весу (не на плече и не в обнимку). Картинка очень конкретная: пальцы продеты в ручку, груз свисает вниз.</p><p>Из этого «приподнять» вырастает переносное: <strong>提问</strong> (задать вопрос), <strong>提到</strong> (упомянуть), <strong>提高</strong> (повысить). Будто ты берёшь тему и приподнимаешь её, чтобы все увидели.</p><p>Редкое чтение <strong>dī</strong> живёт только в паре слов вроде 提防 (dīfáng, остерегаться). В повседневной речи 提 — почти всегда <strong>tí</strong>.</p>",
 "situations": [
  {
   "title": "✦ С сумками",
   "setup": "Предлагаешь помочь донести покупки.",
   "line": "我帮你提包吧。 — «Давай я понесу сумку.»"
  },
  {
   "title": "☁ На встрече",
   "setup": "Хочешь поднять новый вопрос.",
   "line": "我想提一个问题。 — «Я хочу задать один вопрос.»"
  }
 ],
 "examples": [
  {
   "cn": "他{hl}提{/hl}着一个大包。",
   "py": "tā tí zhe yí ge dà bāo.",
   "ru": "Он несёт большую сумку.",
   "note": "包 (bāo) — сумка · 着 (zhe) — длящееся действие"
  },
  {
   "cn": "你能帮我{hl}提{/hl}水吗？",
   "py": "nǐ néng bāng wǒ tí shuǐ ma?",
   "ru": "Можешь помочь мне поднести воду?",
   "note": "帮 (bāng) — помогать"
  },
  {
   "cn": "请不要{hl}提{/hl}这件事。",
   "py": "qǐng bú yào tí zhè jiàn shì.",
   "ru": "Пожалуйста, не упоминай об этом.",
   "note": "件 (jiàn) — счётное слово для дел"
  }
 ],
 "footer_note": "提 — нести за ручку → приподнять тему: 提问, 提到, 提高 · редкое чтение dī в 提防 · HSK 5 (hsk2.0-L5)"
}
