{
 "hanzi": "桃",
 "pinyin": "táo",
 "meaning_ru": "персик (плод и дерево)",
 "meaning_en": "peach (fruit and tree)",
 "radicals": [
  {
   "hz": "木",
   "name": "mù — дерево",
   "note": "Левая часть 桃. Ключ всех деревьев и плодов: 林 (лес), 树 (дерево). Персик растёт на дереве — потому слева «木»"
  },
  {
   "hz": "兆",
   "name": "zhào — даёт звук",
   "note": "Правая часть 桃. Фонетик: подсказывает чтение «táo» (как и в 逃 táo — убегать). Смысл несёт дерево слева"
  }
 ],
 "deep_dive": "<p>桃 — мягкий, сочный, ароматный персик, любимый летний фрукт. Но в китайской культуре персик — это куда больше, чем еда.</p><p>Персик — символ <strong>долголетия и бессмертия</strong>. Есть прекрасная легенда: в саду богини Сиванму (西王母) растут волшебные персики 蟠桃, которые зреют раз в тысячи лет и дают вечную жизнь. Поэтому на дни рождения старшим дарят 寿桃 — булочки в форме персика, желая долгих лет. А <strong>桃花</strong> (táohuā), цветок персика, — символ романтики и любви: про того, кому везёт в любви, говорят 桃花运 — «персиковая удача».</p>",
 "situations": [
  {
   "title": "✦ На рынке",
   "setup": "Покупаешь летние фрукты.",
   "line": "这个桃很甜。 — «Этот персик очень сладкий.»"
  }
 ],
 "examples": [
  {
   "cn": "这个{hl}桃{/hl}很甜。",
   "py": "zhège táo hěn tián.",
   "ru": "Этот персик очень сладкий.",
   "note": "甜 (tián) — сладкий"
  },
  {
   "cn": "我喜欢吃{hl}桃{/hl}。",
   "py": "wǒ xǐhuan chī táo.",
   "ru": "Я люблю есть персики.",
   "note": "喜欢 (xǐhuan) — любить · 吃 — есть"
  },
  {
   "cn": "春天{hl}桃{/hl}花开了。",
   "py": "chūntiān táo huā kāi le.",
   "ru": "Весной зацвели персики.",
   "note": "桃花 (táohuā) — цветок персика · 春天 — весна"
  }
 ],
 "footer_note": "桃 — персик; символ долголетия (寿桃) и любви (桃花运 — везение в любви) · HSK 5 (hsk2.0-L5)"
}
